devjoni/guibase.py
devjoni/hosguibase/backend_gtk.py
devjoni/hosguibase/backend_gtk_video.py
devjoni/hosguibase/backend_p3d.py
devjoni/hosguibase/backend_tk.py
devjoni/hosguibase/common.py
devjoni/hosguibase/directories.py
devjoni/hosguibase/fftranscoder.py
devjoni/hosguibase/guiauto.py
devjoni/hosguibase/guifiledialog.py
devjoni/hosguibase/guiicon.py
devjoni/hosguibase/guiimage.py
devjoni/hosguibase/guiwidgets.py
devjoni/hosguibase/imagefuncs.py
devjoni/hosguibase/render3d.py
devjoni/hosguibase/translations.py
devjoni/hosguibase/version.py
devjoni/hosguibase/video.py
devjoni/hosguibasedata/file.png
devjoni/hosguibasedata/folder.png
devjoni/hosguibasedata/location.py
devjoni/hosguibasedata/menubutton.png
devjoni_hosguibase-0.0.7.dist-info/licenses/LICENSE
devjoni_hosguibase-0.0.7.dist-info/METADATA
devjoni_hosguibase-0.0.7.dist-info/WHEEL
devjoni_hosguibase-0.0.7.dist-info/top_level.txt
devjoni_hosguibase-0.0.7.dist-info/RECORD
