Metadata-Version: 2.4
Name: devjoni-hosguibase
Version: 0.0.7
Summary: A simplified widget toolkit supporting many backends
Author-email: DEV Joni <solutions@devjoni.com>
Project-URL: Homepage, https://github.com/devjonix/hosguibase
Project-URL: Bug Tracker, https://github.com/devjonix/hosguibase/issues
Keywords: toolkit,GUI,tk,gtk,p3d
Classifier: Programming Language :: Python :: 3
Classifier: License :: OSI Approved :: GNU General Public License v3 (GPLv3)
Classifier: Operating System :: OS Independent
Requires-Python: >=3.8
License-File: LICENSE
Dynamic: license-file
